README.rst
setup.py
universe/__init__.py
universe/configuration.py
universe/error.py
universe/runtimes.yml
universe/twisty.py
universe.egg-info/PKG-INFO
universe.egg-info/SOURCES.txt
universe.egg-info/dependency_links.txt
universe.egg-info/requires.txt
universe.egg-info/top_level.txt
universe/envs/__init__.py
universe/envs/diagnostics.py
universe/envs/dummy_vnc_env.py
universe/envs/vnc_env.py
universe/envs/vnc_flashgames.py
universe/envs/vnc_gtav.py
universe/envs/vnc_internet.py
universe/envs/vnc_starcraft.py
universe/envs/vnc_wog.py
universe/envs/tests/__init__.py
universe/envs/tests/test_semantics.py
universe/envs/vnc_core_env/__init__.py
universe/envs/vnc_core_env/key.py
universe/envs/vnc_core_env/translator.py
universe/envs/vnc_core_env/vnc_core_env.py
universe/kube/__init__.py
universe/kube/discovery.py
universe/pyprofile/__init__.py
universe/remotes/__init__.py
universe/remotes/allocator_remote.py
universe/remotes/build.py
universe/remotes/docker_remote.py
universe/remotes/hardcoded_addresses.py
universe/remotes/healthcheck.py
universe/remotes/remote.py
universe/remotes/compose/__init__.py
universe/remotes/compose/colors.py
universe/remotes/compose/container.py
universe/remotes/compose/log_printer.py
universe/remotes/compose/progress_stream.py
universe/remotes/compose/signals.py
universe/remotes/compose/utils.py
universe/rewarder/__init__.py
universe/rewarder/connection_timer.py
universe/rewarder/env_status.py
universe/rewarder/merge.py
universe/rewarder/remote.py
universe/rewarder/reward_buffer.py
universe/rewarder/reward_proxy_server.py
universe/rewarder/rewarder_client.py
universe/rewarder/rewarder_session.py
universe/runtimes/__init__.py
universe/runtimes/registration.py
universe/scoreboard/__init__.py
universe/spaces/__init__.py
universe/spaces/diagnostics.py
universe/spaces/hardcoded.py
universe/spaces/joystick_action_space.py
universe/spaces/joystick_event.py
universe/spaces/vnc_action_space.py
universe/spaces/vnc_event.py
universe/spaces/vnc_observation_space.py
universe/utils/__init__.py
universe/utils/display.py
universe/vectorized/__init__.py
universe/vectorized/core.py
