Metadata-Version: 1.0
Name: universe
Version: 0.21.2
Summary: Universe: a software platform for measuring and training an AI's general intelligence across the world's supply of games, websites and other applications.
Home-page: https://github.com/openai/universe
Author: OpenAI
Author-email: universe@openai.com
License: UNKNOWN
Platform: UNKNOWN
